framewirc/parsers.py
framewirc/__init__.py
framewirc/exceptions.py
framewirc/commands.py
framewirc/client.py
framewirc/message.py
framewirc/filters.py
framewirc/utils.py
framewirc/connection.py
framewirc/handlers.py
framewirc-0.1.0.dist-info/metadata.json
framewirc-0.1.0.dist-info/top_level.txt
framewirc-0.1.0.dist-info/METADATA
framewirc-0.1.0.dist-info/DESCRIPTION.rst
framewirc-0.1.0.dist-info/RECORD
framewirc-0.1.0.dist-info/WHEEL
