Metadata-Version: 2.0
Name: framewirc
Version: 0.1.0
Summary: An asynchronous IRC framework/library based upon asyncio
Home-page: https://github.com/meshy/framewirc/
Author: Charlie Denton
Author-email: charlie@meshy.co.uk
License: UNKNOWN
Platform: UNKNOWN
Classifier: Development Status :: 2 - Pre-Alpha
Classifier: Intended Audience :: Developers
Classifier: License :: OSI Approved :: BSD License
Classifier: Natural Language :: English
Classifier: Programming Language :: Python :: 3
Classifier: Programming Language :: Python :: 3.4
Classifier: Programming Language :: Python :: 3.5
Classifier: Programming Language :: Python :: 3 :: Only
Classifier: Topic :: Communications :: Chat :: Internet Relay Chat
Requires-Dist: cchardet (>=0.3.5,<2)
